mcp_knowledge_query/__init__.py
mcp_knowledge_query/__main__.py
mcp_knowledge_query/client.py
mcp_knowledge_query/query_knowledge.py
mcp_knowledge_query/server.py
mcp_knowledge_query_kd-0.1.1.dist-info/METADATA
mcp_knowledge_query_kd-0.1.1.dist-info/WHEEL
mcp_knowledge_query_kd-0.1.1.dist-info/entry_points.txt
mcp_knowledge_query_kd-0.1.1.dist-info/RECORD
