Metadata-Version: 2.4
Name: mcp-knowledge-query-kd
Version: 0.1.1
Summary: MCP server for querying internal knowledge base
Author-email: Your Name <your.email@example.com>
Requires-Python: >=3.10
Requires-Dist: build>=1.4.0
Requires-Dist: mcp[cli]>=1.25.0
Requires-Dist: requests>=2.32.5
Requires-Dist: twine>=6.2.0
Requires-Dist: volcengine>=1.0.213
